pgcli/__init__.py
pgcli/__main__.py
pgcli/auth.py
pgcli/completion_refresher.py
pgcli/config.py
pgcli/explain_output_formatter.py
pgcli/key_bindings.py
pgcli/magic.py
pgcli/main.py
pgcli/pgbuffer.py
pgcli/pgclirc
pgcli/pgcompleter.py
pgcli/pgexecute.py
pgcli/pgstyle.py
pgcli/pgtoolbar.py
pgcli/pyev.py
pgcli/packages/__init__.py
pgcli/packages/prioritization.py
pgcli/packages/prompt_utils.py
pgcli/packages/sqlcompletion.py
pgcli/packages/formatter/__init__.py
pgcli/packages/formatter/sqlformatter.py
pgcli/packages/parseutils/__init__.py
pgcli/packages/parseutils/ctes.py
pgcli/packages/parseutils/meta.py
pgcli/packages/parseutils/tables.py
pgcli/packages/parseutils/utils.py
pgcli/packages/pgliterals/__init__.py
pgcli/packages/pgliterals/main.py
pgcli/packages/pgliterals/pgliterals.json
pgcli-4.2.0.dist-info/AUTHORS
pgcli-4.2.0.dist-info/LICENSE.txt
pgcli-4.2.0.dist-info/METADATA
pgcli-4.2.0.dist-info/WHEEL
pgcli-4.2.0.dist-info/entry_points.txt
pgcli-4.2.0.dist-info/top_level.txt
pgcli-4.2.0.dist-info/RECORD
