Metadata-Version: 2.2
Name: pgcli
Version: 4.2.0
Summary: CLI for Postgres Database. With auto-completion and syntax highlighting.
Author-email: Pgcli Core Team <pgcli-dev@googlegroups.com>
License: BSD
Project-URL: Homepage, https://pgcli.com
Classifier: Intended Audience :: Developers
Classifier: License :: OSI Approved :: BSD License
Classifier: Operating System :: Unix
Classifier: Programming Language :: Python
Classifier: Programming Language :: Python :: 3
Classifier: Programming Language :: Python :: 3.9
Classifier: Programming Language :: Python :: 3.10
Classifier: Programming Language :: Python :: 3.11
Classifier: Programming Language :: Python :: 3.12
Classifier: Programming Language :: Python :: 3.13
Classifier: Programming Language :: SQL
Classifier: Topic :: Database
Classifier: Topic :: Database :: Front-Ends
Classifier: Topic :: Software Development
Classifier: Topic :: Software Development :: Libraries :: Python Modules
Requires-Python: >=3.9
License-File: LICENSE.txt
License-File: AUTHORS
Requires-Dist: pgspecial>=2.0.0
Requires-Dist: click>=4.1
Requires-Dist: Pygments>=2.0
Requires-Dist: prompt_toolkit<4.0.0,>=2.0.6
Requires-Dist: psycopg>=3.0.14; sys_platform != "win32"
Requires-Dist: psycopg-binary>=3.0.14; sys_platform == "win32"
Requires-Dist: sqlparse<0.6,>=0.3.0
Requires-Dist: configobj>=5.0.6
Requires-Dist: cli_helpers[styles]>=2.2.1
Requires-Dist: setproctitle>=1.1.9; sys_platform != "win32" and "CYGWIN" not in sys_platform
Provides-Extra: keyring
Requires-Dist: keyring>=12.2.0; extra == "keyring"
Provides-Extra: sshtunnel
Requires-Dist: sshtunnel>=0.4.0; extra == "sshtunnel"
